setup.py
repi_server/__init__.py
repi_server/command_line.py
repi_server/connection.py
repi_server/repi_server.py
repi_server.egg-info/PKG-INFO
repi_server.egg-info/SOURCES.txt
repi_server.egg-info/dependency_links.txt
repi_server.egg-info/entry_points.txt
repi_server.egg-info/not-zip-safe
repi_server.egg-info/requires.txt
repi_server.egg-info/top_level.txt