Metadata-Version: 1.1
Name: repi-server
Version: 0.2
Summary: RePi server, a Redis PubSub interface for PyPi.
Home-page: http://github.com/vortec/repi-server
Author: Fabian Kochem
Author-email: fkochem@gmail.com
License: MIT
Platform: UNKNOWN
Classifier: Environment :: Console
Classifier: Intended Audience :: System Administrators
Classifier: License :: OSI Approved :: MIT License
Classifier: Operating System :: POSIX
Classifier: Programming Language :: Python :: 2.7
Classifier: Topic :: System :: Software Distribution
